datto/CleanDataframe.py
datto/DataConnections.py
datto/Eda.py
datto/Experiments.py
datto/FrontEnd.py
datto/ModelResults.py
datto/SetupMethods.py
datto/TrainModel.py
datto/__init__.py
datto/data/__init__.py
datto/data/all_names
datto/utils.py
datto-0.9.1.dist-info/LICENSE
datto-0.9.1.dist-info/WHEEL
datto-0.9.1.dist-info/METADATA
datto-0.9.1.dist-info/RECORD
