Metadata-Version: 2.1
Name: datto
Version: 0.9.1
Summary: Data Tools (Dat To)
Author: kristiewirth
Author-email: kristie.ann.wirth@gmail.com
Requires-Python: >=3.8,<3.11
Classifier: Programming Language :: Python :: 3
Classifier: Programming Language :: Python :: 3.10
Classifier: Programming Language :: Python :: 3.8
Classifier: Programming Language :: Python :: 3.9
Provides-Extra: docs
Requires-Dist: catboost (>=1.1.1,<2.0.0)
Requires-Dist: gensim (==3.7.3)
Requires-Dist: hypothesis (>=6.70.0,<7.0.0)
Requires-Dist: jupytext (>=1.14.5,<2.0.0)
Requires-Dist: lime (>=0.2.0,<0.3.0)
Requires-Dist: nbconvert (>=7.2.10,<8.0.0)
Requires-Dist: nltk (>=3.8.1,<4.0.0)
Requires-Dist: numpy (==1.23.5)
Requires-Dist: pandas (>=1.5.3,<2.0.0)
Requires-Dist: progressbar (>=2.5,<3.0)
Requires-Dist: psycopg2-binary (>=2.9.5,<3.0.0)
Requires-Dist: pytest (>=7.2.2,<8.0.0)
Requires-Dist: python-json-logger (>=2.0.7,<3.0.0)
Requires-Dist: s3fs (>=2023.3.0,<2024.0.0)
Requires-Dist: scikit-learn (==1.1.3)
Requires-Dist: seaborn (>=0.12.2,<0.13.0)
Requires-Dist: shap (>=0.41.0,<0.42.0)
Requires-Dist: slack-client (>=0.3.0,<0.4.0)
Requires-Dist: slack-sdk (>=3.20.2,<4.0.0)
Requires-Dist: spacy (>=3.5.1,<4.0.0)
Requires-Dist: sphinx (>=4.3.0,<5.0.0); extra == "docs"
Requires-Dist: sphinx-rtd-theme (>=1.2.0,<2.0.0)
Requires-Dist: statsmodels (>=0.13.5,<0.14.0)
Requires-Dist: tabulate (>=0.9.0,<0.10.0)
Requires-Dist: xgboost (>=1.7.4,<2.0.0)
